gp_test_dep1/__init__.py
gp_test_dep1/sample.py
gp_test_dep1-1.0.1.dist-info/METADATA
gp_test_dep1-1.0.1.dist-info/WHEEL
gp_test_dep1-1.0.1.dist-info/top_level.txt
gp_test_dep1-1.0.1.dist-info/RECORD
