Metadata-Version: 2.1
Name: gp_test_dep1
Version: 1.0.1
Summary: A sample Python module named gp_test_dep1
Home-page: https://github.com/yourusername/gp_test_dep1
Author: Your Name
Author-email: your.email@example.com
Classifier: Programming Language :: Python :: 3
Classifier: License :: OSI Approved :: MIT License
Classifier: Operating System :: OS Independent
Requires-Python: >=3.8
Requires-Dist: gp-test-dep2>=1.0.0
